abhi/__init__.py
abhi/abhiDarekar.py
abhiDarekar-1.0.0.dist-info/LICENSE
abhiDarekar-1.0.0.dist-info/METADATA
abhiDarekar-1.0.0.dist-info/WHEEL
abhiDarekar-1.0.0.dist-info/top_level.txt
abhiDarekar-1.0.0.dist-info/RECORD
