Metadata-Version: 2.1
Name: abhiDarekar
Version: 1.0.0
Summary: This is a test python package created by abhishek
Home-page: UNKNOWN
Author: Abhishek Darekar
License: MIT
Platform: UNKNOWN
Classifier: License :: OSI Approved :: MIT License
Classifier: Programming Language :: Python :: 3.9
License-File: LICENSE
